mongo_statsd/__init__.py
mongo_statsd/constants.py
mongo_statsd/stat_reader.py
mongo_statsd/stat_reporter.py
mongo_statsd-1.0.6.data/scripts/run_mongo_statsd.py
mongo_statsd-1.0.6.dist-info/METADATA
mongo_statsd-1.0.6.dist-info/WHEEL
mongo_statsd-1.0.6.dist-info/top_level.txt
mongo_statsd-1.0.6.dist-info/RECORD
