Metadata-Version: 2.1
Name: mongo-statsd
Version: 1.0.6
Summary: upload mongodb stat to statsd
Home-page: https://github.com/dantezhu/mongo_statsd
Author: dantezhu
Author-email: dantezhu <zny2008@gmail.com>
License: MIT
Project-URL: Homepage, https://github.com/dantezhu/mongo_statsd
Platform: any
Requires-Dist: statsd
